setup.cfg
setup.py
mercadolibre/__init__.py
mercadolibre/api.py
mercadolibre/auth.py
mercadolibre/config.py
mercadolibre/exceptions.py
mercadolibre/http.py
mercadolibre/iterators.py
mercadolibre/resources.py
mercadolibre.py.egg-info/PKG-INFO
mercadolibre.py.egg-info/SOURCES.txt
mercadolibre.py.egg-info/dependency_links.txt
mercadolibre.py.egg-info/not-zip-safe
mercadolibre.py.egg-info/requires.txt
mercadolibre.py.egg-info/top_level.txt