Metadata-Version: 1.1
Name: mercadolibre.py
Version: 0.1.7
Summary: Mercadolibre Python SDK (for humans)
Home-page: https://github.com/santiagobasulto/mercadolibre.py
Author: Santiago Basulto
Author-email: santiago.basulto@gmail.com
License: MIT
Download-URL: https://github.com/santiagobasulto/mercadolibre.py/tarball/0.1.7
Platform: UNKNOWN
Classifier: Development Status :: 4 - Beta
Classifier: Intended Audience :: Developers
Classifier: Natural Language :: English
Classifier: License :: OSI Approved :: MIT License
Classifier: Programming Language :: Python
Classifier: Programming Language :: Python :: 2.7
Classifier: Programming Language :: Python :: 3
Classifier: Programming Language :: Python :: 3.3
Classifier: Programming Language :: Python :: 3.4
